unifhycontrib_smart-0.1.1-py3.8-nspkg.pth
unifhycontrib/smart/__init__.py
unifhycontrib/smart/openwater.py
unifhycontrib/smart/subsurface.py
unifhycontrib/smart/surfacelayer.py
unifhycontrib/smart/version.py
unifhycontrib_smart-0.1.1.dist-info/METADATA
unifhycontrib_smart-0.1.1.dist-info/WHEEL
unifhycontrib_smart-0.1.1.dist-info/namespace_packages.txt
unifhycontrib_smart-0.1.1.dist-info/top_level.txt
unifhycontrib_smart-0.1.1.dist-info/RECORD
