Metadata-Version: 2.1
Name: unifhycontrib-smart
Version: 0.1.1
Summary: unifhy components for the SMART model
Author: Thibault Hallouin, Eva M. Mockler, Michael Bruen
License: GPL-3.0
Project-URL: Source Code, https://github.com/unifhy-org/unifhycontrib-smart
Platform: UNKNOWN
Classifier: Development Status :: 4 - Beta
Classifier: Natural Language :: English
Classifier: Topic :: Scientific/Engineering :: Hydrology
Requires-Dist: unifhy (>=0.1.0)
Provides-Extra: tests
Requires-Dist: cf-python ; extra == 'tests'
